[
  {
    "title": "Airplane Mode",
    "id": "73197748961359",
    "cover": "https://cdn-images.dzcdn.net/images/cover/0128fc8d42fecd844043b40ed8c45dd6/0x1900-000000-80-0-0.jpg",
    "tags": [
      "CHILL-POP"
    ]
  },
  {
    "title": "Sweet Little Bumblebee [Jumpstyle]",
    "id": "128961712071619",
    "cover": "https://encrypted-tbn0.gstatic.com/images?q=tbn:ANd9GcRykhs-AUVLy_EIdLVvsWRdcT6Z0NSWybGyXA&s",
    "tags": [
      "JUMPSTYLE"
    ]
  },
  {
    "title": "Has To Be",
    "id": "137585563394909",
    "cover": "https://encrypted-tbn0.gstatic.com/images?q=tbn:ANd9GcSorTYYEDWsVVfRJHkD8C99h6uZgPsRiaBEnA&s",
    "tags": [
      "TRAP"
    ]
  },
  {
    "title": "Montagem Sanor",
    "id": "113425320169497",
    "cover": "https://is1-ssl.mzstatic.com/image/thumb/Music211/v4/b0/20/a3/b020a3b4-8670-5f14-a01f-e8486121808c/artwork.jpg/316x316bb.webp",
    "tags": [
      "FUNK"
    ]
  },
  {
    "title": "Freaks",
    "id": "118545811050500",
    "cover": "https://encrypted-tbn0.gstatic.com/images?q=tbn:ANd9GcSt-oM7ig-HOhVMvmNvUqYF83zT6QVDVzY9WA&s",
    "tags": [
      "SURF ROCK",
      "INDIE"
    ]
  },
  {
    "title": "NUMBER",
    "id": "82696338249251",
    "cover": "https://i.scdn.co/image/ab67616d00001e02df40c5724b757ae5411c9722",
    "tags": [
      "HARDTEKK"
    ]
  },
  {
    "title": "FUNK DO MIRRORS",
    "id": "73295033713326",
    "cover": "https://i.scdn.co/image/ab67616d00001e021117bc9cd926c2bd3cfda259",
    "tags": [
      "FUNK"
    ]
  },
  {
    "title": "Countin Stars",
    "id": "118957335322667",
    "cover": "https://i1.sndcdn.com/artworks-000108154780-rggyav-t500x500.jpg",
    "tags": [
      "DRILL",
      "POP"
    ]
  },
  {
    "title": "RETOLAM FUNK",
    "id": "90359988371949",
    "cover": "https://cdn-images.dzcdn.net/images/cover/815cc0310495f3fd9efa8efd69dd9fc4/0x1900-000000-80-0-0.jpg",
    "tags": [
      "FUNK",
      "CHILL"
    ]
  },
  {
    "title": "nuts",
    "id": "98839453510161",
    "cover": "https://i.scdn.co/image/ab67616d0000b27309d54dc63b8d61cef9e977e5",
    "tags": [
      "TRAP"
    ]
  },
  {
    "title": "MOONLIGHT FUNK",
    "id": "98627387177279",
    "cover": "https://encrypted-tbn0.gstatic.com/images?q=tbn:ANd9GcSdZ-CDTimQx1fd2OL-Wcxh899rP9ToyyYWRQ&s",
    "tags": [
      "FUNK"
    ]
  },
  {
    "title": "I Got No Time",
    "id": "89258052168328",
    "cover": "https://encrypted-tbn0.gstatic.com/images?q=tbn:ANd9GcQYrAH4P8vNJbf7PFfdLvNME5w8FzYnGQ9FAw&s",
    "tags": [
      "DANCE",
      "ELETRONIC"
    ]
  },
  {
    "title": "Mimosa 2000",
    "id": "137329447492960",
    "cover": "https://encrypted-tbn0.gstatic.com/images?q=tbn:ANd9GcSAnz86UatdtpfN1YcH65o4dHBiI4dtrHYgEQ&s",
    "tags": [
      "FUNK BRASILEIRO"
    ]
  },
  {
    "title": "Stay With Me (Phonk)",
    "id": "88349464000927",
    "cover": "https://i1.sndcdn.com/artworks-ZKjw28i7pvOYYaMm-lyOJNA-t500x500.jpg",
    "tags": [
      "PHONK"
    ]
  }
]
